CHANGELOG.rst
MANIFEST.in
README.rst
setup.cfg
setup.py
async_v20/__init__.py
async_v20/client.py
async_v20/exceptions.py
async_v20.egg-info/PKG-INFO
async_v20.egg-info/SOURCES.txt
async_v20.egg-info/dependency_links.txt
async_v20.egg-info/requires.txt
async_v20.egg-info/top_level.txt
async_v20/definitions/__init__.py
async_v20/definitions/attributes.py
async_v20/definitions/base.py
async_v20/definitions/health_types.py
async_v20/definitions/helpers.py
async_v20/definitions/primitives.py
async_v20/definitions/types.py
async_v20/endpoints/__init__.py
async_v20/endpoints/account.py
async_v20/endpoints/annotations.py
async_v20/endpoints/base.py
async_v20/endpoints/health.py
async_v20/endpoints/instrument.py
async_v20/endpoints/order.py
async_v20/endpoints/other_responses.py
async_v20/endpoints/position.py
async_v20/endpoints/pricing.py
async_v20/endpoints/trade.py
async_v20/endpoints/transaction.py
async_v20/endpoints/user.py
async_v20/interface/__init__.py
async_v20/interface/account.py
async_v20/interface/decorators.py
async_v20/interface/health.py
async_v20/interface/helpers.py
async_v20/interface/instrument.py
async_v20/interface/order.py
async_v20/interface/parser.py
async_v20/interface/position.py
async_v20/interface/pricing.py
async_v20/interface/response.py
async_v20/interface/rest.py
async_v20/interface/trade.py
async_v20/interface/transaction.py
async_v20/interface/user.py
bin/__init__.py
bin/account.py
bin/account_changes.py
bin/candle_data.py
bin/candles.py
bin/check_api_methods.py
bin/concurrent_example.py
bin/data_download_tool.py
bin/initialization.py
bin/passing_arguments.py
bin/place_order.py
bin/poll_account.py
bin/preload.py
bin/stream_prices.py
bin/stream_transactions.py
perftests/__init__.py
perftests/account_changes_json.py
perftests/creating_arrays.py
perftests/creating_dataframe.py
perftests/creating_orders.py
perftests/helpers.py
perftests/rest_implementation.py
perftests/server.py
tests/__init__.py
tests/test_client.py
tests/test_server_fixture.py
tests/data/__init__.py
tests/data/json_data.py
tests/fixtures/__init__.py
tests/fixtures/client.py
tests/fixtures/routes.py
tests/fixtures/server.py
