Metadata-Version: 1.1
Name: async-v20
Version: 8.0.0b1
Summary: Asynchronous wrapper for OANDA's v20 REST API
Home-page: https://github.com/jamespeterschinner/async_v20
Author: James Peter Schinner
Author-email: james.peter.schinner@gmail.com
License: MIT
Keywords: algorithmic trading oanda v20 REST asyncio
Platform: UNKNOWN
Classifier: Programming Language :: Python :: 3.6
Classifier: Development Status :: 4 - Beta
Classifier: Framework :: AsyncIO
Classifier: Intended Audience :: Developers
Classifier: License :: OSI Approved :: MIT License
Classifier: Operating System :: OS Independent
Classifier: Topic :: Internet :: WWW/HTTP :: Session
